knx.py
knx-0.4.0.dist-info/LICENSE
knx-0.4.0.dist-info/METADATA
knx-0.4.0.dist-info/WHEEL
knx-0.4.0.dist-info/top_level.txt
knx-0.4.0.dist-info/RECORD
