Metadata-Version: 2.1
Name: knx
Version: 0.4.0
Summary: KNX / EIB library
Home-page: https://github.com/mfussenegger/knx
Author: Mathias Fußenegger
Author-email: pip@zignar.net
License: MIT
Platform: any
Classifier: Development Status :: 4 - Beta
Classifier: Programming Language :: Python :: 3
Classifier: Programming Language :: Python :: 3.6
Classifier: Programming Language :: Python :: 3.7
Classifier: License :: OSI Approved :: MIT License
